ooba/__init__.py
ooba/download.py
ooba/install.py
ooba/llm.py
ooba/test.py
ooba/tests/__init__.py
ooba/tests/test_ooba.py
ooba/uninstall.py
ooba/utils/detect_hardware.py
ooba/utils/ensure_repo_exists.py
ooba/utils/get_app_dir.py
ooba/utils/get_latest_release.py
ooba/utils/get_open_ports.py
ooba/utils/list_gguf_files.py
ooba/utils/openai_messages_converters.py
ooba-0.0.22.dist-info/LICENSE
ooba-0.0.22.dist-info/METADATA
ooba-0.0.22.dist-info/WHEEL
ooba-0.0.22.dist-info/RECORD
