Metadata-Version: 2.1
Name: ooba
Version: 0.0.22
Summary: Run language models on consumer hardware.
License: AGPL
Author: Killian Lucas
Author-email: killian@openinterpreter.com
Requires-Python: >=3.9,<4.0
Classifier: License :: Other/Proprietary License
Classifier: Programming Language :: Python :: 3
Classifier: Programming Language :: Python :: 3.9
Classifier: Programming Language :: Python :: 3.10
Classifier: Programming Language :: Python :: 3.11
Requires-Dist: appdirs (>=1.4.4,<2.0.0)
Requires-Dist: huggingface-hub (>=0.17.3,<0.18.0)
Requires-Dist: websockets (>=11.0.3,<12.0.0)
